{
  "underlying": "BANKNIFTY",
  "start": "2026-02-10",
  "end": "2026-02-23",
  "interval": 5,
  "expiry_offset": 0,
  "stats": {
    "trades": 9,
    "wins": 3,
    "losses": 6,
    "win_rate": 33.33,
    "net_pnl": 5733.63,
    "gross_profit": 13934.82,
    "gross_loss": 8201.19,
    "profit_factor": 1.6991,
    "avg_trade": 637.07,
    "avg_win": 4644.94,
    "avg_loss": -1366.87,
    "max_drawdown": -5237.8
  },
  "equity_curve": [
    -2647.72,
    -2861.52,
    1588.16,
    1559.55,
    1486.29,
    6047.6,
    10971.43,
    8335.03,
    5733.63
  ],
  "trades": [
    {
      "underlying": "BANKNIFTY",
      "day": "2026-02-10",
      "expiry": "2026-02-24",
      "entry_time": "2026-02-10T10:30:00",
      "exit_time": "2026-02-10T15:15:00",
      "signal_type": "BUY_CE",
      "strategy_name": "Bullish OI Wall Breakout",
      "score": 80,
      "strength": "VALID",
      "strike": 60800,
      "opt_type": "CE",
      "qty": 30,
      "entry_price": 514.15,
      "exit_price": 428.3,
      "exit_reason": "TIME",
      "gross_pnl": -2575.5,
      "cost": 72.22,
      "net_pnl": -2647.72,
      "entry_spot": 60833.4,
      "reasons": [
        "Spot 60833.40 is above VWAP 60772.55",
        "5-minute close broke CE wall 60700",
        "60800 PE OI changed 11.7%",
        "Volume is 2.2x average",
        "ATM CE premium changed 5.2%"
      ]
    },
    {
      "underlying": "BANKNIFTY",
      "day": "2026-02-11",
      "expiry": "2026-02-24",
      "entry_time": "2026-02-11T11:30:00",
      "exit_time": "2026-02-11T15:15:00",
      "signal_type": "BUY_CE",
      "strategy_name": "Bullish OI Wall Breakout",
      "score": 80,
      "strength": "VALID",
      "strike": 60800,
      "opt_type": "CE",
      "qty": 30,
      "entry_price": 462.8,
      "exit_price": 458.1,
      "exit_reason": "TIME",
      "gross_pnl": -141.0,
      "cost": 72.8,
      "net_pnl": -213.8,
      "entry_spot": 60810.0,
      "reasons": [
        "Spot 60810.00 is above VWAP 60711.99",
        "5-minute close broke CE wall 60700",
        "60800 PE OI changed 8.3%",
        "Volume is 2.6x average",
        "ATM CE premium changed 5.1%"
      ]
    },
    {
      "underlying": "BANKNIFTY",
      "day": "2026-02-16",
      "expiry": "2026-02-24",
      "entry_time": "2026-02-16T12:25:00",
      "exit_time": "2026-02-16T15:15:00",
      "signal_type": "BUY_CE",
      "strategy_name": "Bullish OI Wall Breakout",
      "score": 100,
      "strength": "STRONG",
      "strike": 60700,
      "opt_type": "CE",
      "qty": 30,
      "entry_price": 425.6,
      "exit_price": 576.5,
      "exit_reason": "TIME",
      "gross_pnl": 4527.0,
      "cost": 77.32,
      "net_pnl": 4449.68,
      "entry_spot": 60692.0,
      "reasons": [
        "Spot 60692.00 is above VWAP 60420.96",
        "5-minute close broke CE wall 60500",
        "60500 CE OI changed -8.1%",
        "60600 PE OI changed 18.3%",
        "Volume is 2.9x average",
        "ATM CE premium changed 20.1%"
      ]
    },
    {
      "underlying": "BANKNIFTY",
      "day": "2026-02-17",
      "expiry": "2026-02-24",
      "entry_time": "2026-02-17T10:25:00",
      "exit_time": "2026-02-17T15:15:00",
      "signal_type": "BUY_CE",
      "strategy_name": "Bullish OI Wall Breakout",
      "score": 80,
      "strength": "VALID",
      "strike": 61000,
      "opt_type": "CE",
      "qty": 30,
      "entry_price": 445.8,
      "exit_price": 447.25,
      "exit_reason": "TIME",
      "gross_pnl": 43.5,
      "cost": 72.11,
      "net_pnl": -28.61,
      "entry_spot": 61050.0,
      "reasons": [
        "Spot 61050.00 is above VWAP 60810.06",
        "5-minute close broke CE wall 61000",
        "61000 PE OI changed 10.2%",
        "Volume is 1.8x average",
        "ATM CE premium changed 15.8%"
      ]
    },
    {
      "underlying": "BANKNIFTY",
      "day": "2026-02-18",
      "expiry": "2026-02-24",
      "entry_time": "2026-02-18T14:20:00",
      "exit_time": "2026-02-18T15:15:00",
      "signal_type": "BUY_CE",
      "strategy_name": "Bullish OI Wall Breakout",
      "score": 100,
      "strength": "STRONG",
      "strike": 61500,
      "opt_type": "CE",
      "qty": 30,
      "entry_price": 333.25,
      "exit_price": 333.0,
      "exit_reason": "TIME",
      "gross_pnl": -7.5,
      "cost": 65.76,
      "net_pnl": -73.26,
      "entry_spot": 61472.0,
      "reasons": [
        "Spot 61472.00 is above VWAP 61236.62",
        "5-minute close broke CE wall 61000",
        "61000 CE OI changed -6.6%",
        "61400 PE OI changed 13.6%",
        "Volume is 5.7x average",
        "ATM CE premium changed 32.5%"
      ]
    },
    {
      "underlying": "BANKNIFTY",
      "day": "2026-02-19",
      "expiry": "2026-02-24",
      "entry_time": "2026-02-19T10:35:00",
      "exit_time": "2026-02-19T12:40:00",
      "signal_type": "BUY_PE",
      "strategy_name": "Bearish OI Wall Breakdown",
      "score": 80,
      "strength": "VALID",
      "strike": 61200,
      "opt_type": "PE",
      "qty": 30,
      "entry_price": 303.95,
      "exit_price": 458.35,
      "exit_reason": "TARGET",
      "gross_pnl": 4632.0,
      "cost": 70.69,
      "net_pnl": 4561.31,
      "entry_spot": 61243.6,
      "reasons": [
        "Spot 61243.60 is below VWAP 61390.34",
        "5-minute close broke PE wall 61500",
        "61500 PE OI changed -6.9%",
        "Volume is 1.9x average",
        "ATM PE premium changed 11.5%"
      ]
    },
    {
      "underlying": "BANKNIFTY",
      "day": "2026-02-20",
      "expiry": "2026-02-24",
      "entry_time": "2026-02-20T09:45:00",
      "exit_time": "2026-02-20T12:20:00",
      "signal_type": "BUY_CE",
      "strategy_name": "Bullish OI Wall Breakout",
      "score": 80,
      "strength": "VALID",
      "strike": 61100,
      "opt_type": "CE",
      "qty": 30,
      "entry_price": 330.25,
      "exit_price": 496.8,
      "exit_reason": "TARGET",
      "gross_pnl": 4996.5,
      "cost": 72.67,
      "net_pnl": 4923.83,
      "entry_spot": 61099.0,
      "reasons": [
        "Spot 61099.00 is above VWAP 60940.98",
        "5-minute close broke CE wall 61000",
        "61000 PE OI changed 27.5%",
        "Volume is 1.7x average",
        "ATM CE premium changed 26.5%"
      ]
    },
    {
      "underlying": "BANKNIFTY",
      "day": "2026-02-23",
      "expiry": "2026-02-24",
      "entry_time": "2026-02-23T10:45:00",
      "exit_time": "2026-02-23T11:05:00",
      "signal_type": "BUY_PE",
      "strategy_name": "Bearish OI Wall Breakdown",
      "score": 85,
      "strength": "STRONG",
      "strike": 61200,
      "opt_type": "PE",
      "qty": 30,
      "entry_price": 311.15,
      "exit_price": 225.3,
      "exit_reason": "SL",
      "gross_pnl": -2575.5,
      "cost": 60.9,
      "net_pnl": -2636.4,
      "entry_spot": 61170.0,
      "reasons": [
        "Spot 61170.00 is below VWAP 61304.37",
        "5-minute close broke PE wall 61300",
        "61300 PE OI changed -20.6%",
        "61200 CE OI changed 5.4%",
        "ATM PE premium changed 8.8%"
      ]
    },
    {
      "underlying": "BANKNIFTY",
      "day": "2026-02-23",
      "expiry": "2026-02-24",
      "entry_time": "2026-02-23T12:30:00",
      "exit_time": "2026-02-23T14:30:00",
      "signal_type": "BUY_PE",
      "strategy_name": "Bearish OI Wall Breakdown",
      "score": 75,
      "strength": "VALID",
      "strike": 61100,
      "opt_type": "PE",
      "qty": 30,
      "entry_price": 274.35,
      "exit_price": 189.6,
      "exit_reason": "SL",
      "gross_pnl": -2542.5,
      "cost": 58.9,
      "net_pnl": -2601.4,
      "entry_spot": 61086.6,
      "reasons": [
        "Spot 61086.60 is below VWAP 61260.11",
        "5-minute close broke PE wall 61200",
        "61200 PE OI changed -11.6%",
        "61100 CE OI changed 10.5%"
      ]
    }
  ],
  "daily": [
    {
      "day": "2026-02-10",
      "trades": 1,
      "net_pnl": -2647.72,
      "skip_reason": ""
    },
    {
      "day": "2026-02-11",
      "trades": 1,
      "net_pnl": -213.8,
      "skip_reason": ""
    },
    {
      "day": "2026-02-12",
      "trades": 0,
      "net_pnl": 0,
      "skip_reason": "no_valid_signal"
    },
    {
      "day": "2026-02-13",
      "trades": 0,
      "net_pnl": 0,
      "skip_reason": "no_valid_signal"
    },
    {
      "day": "2026-02-16",
      "trades": 1,
      "net_pnl": 4449.68,
      "skip_reason": ""
    },
    {
      "day": "2026-02-17",
      "trades": 1,
      "net_pnl": -28.61,
      "skip_reason": ""
    },
    {
      "day": "2026-02-18",
      "trades": 1,
      "net_pnl": -73.26,
      "skip_reason": ""
    },
    {
      "day": "2026-02-19",
      "trades": 1,
      "net_pnl": 4561.31,
      "skip_reason": ""
    },
    {
      "day": "2026-02-20",
      "trades": 1,
      "net_pnl": 4923.83,
      "skip_reason": ""
    },
    {
      "day": "2026-02-23",
      "trades": 2,
      "net_pnl": -5237.8,
      "skip_reason": ""
    }
  ],
  "checked_bars": 377,
  "no_trade_bars": 368,
  "data_quality": {
    "mode": "historical",
    "real_bid_ask": "unavailable",
    "futures_oi": "unavailable",
    "event_calendar": "unavailable",
    "fo_ban_filter": "unavailable",
    "spread_filter": "not_applied_without_real_bid_ask"
  },
  "config": {
    "min_option_oi": 10000,
    "min_option_volume": 5000,
    "max_bid_ask_spread_percent": 3.0,
    "min_option_ltp": 5.0,
    "oi_wall_multiplier": 1.5,
    "ce_unwinding_threshold_percent": -5.0,
    "pe_unwinding_threshold_percent": -5.0,
    "ce_buildup_threshold_percent": 5.0,
    "pe_buildup_threshold_percent": 5.0,
    "volume_multiplier": 1.5,
    "min_signal_score": 75,
    "strong_signal_score": 85,
    "no_trade_first_minutes": 15,
    "no_fresh_trade_after": "14:45",
    "force_exit_time": "15:15",
    "premium_sl_percent": 25,
    "premium_target_percent": 50,
    "trailing_sl_percent": 30,
    "max_trades_per_day": 3,
    "monitor_strikes": 5
  }
}